MANIFEST.in
README
setup.py
kennytestupload/BasicDemo.py
kennytestupload/ClassUsage.py
kennytestupload/Collision.py
kennytestupload/Features.py
kennytestupload/Main.py
kennytestupload/SpaceInvader.py
kennytestupload/Tets.py
kennytestupload/__init__.py
kennytestupload/__init__.spec
kennytestupload/__main__.py
kennytestupload.egg-info/PKG-INFO
kennytestupload.egg-info/SOURCES.txt
kennytestupload.egg-info/dependency_links.txt
kennytestupload.egg-info/top_level.txt
kennytestupload/data/.DS_Store
kennytestupload/data/BGR.png
kennytestupload/data/Sky.png
kennytestupload/data/alien1.gif
kennytestupload/data/alien1.jpg
kennytestupload/data/alien1.png
kennytestupload/data/alien2.gif
kennytestupload/data/alien2.png
kennytestupload/data/alien3.gif
kennytestupload/data/alien3.png
kennytestupload/data/arraydemo.bmp
kennytestupload/data/asprite.bmp
kennytestupload/data/background.gif
kennytestupload/data/black.ppm
kennytestupload/data/blue.gif
kennytestupload/data/blue.mpg
kennytestupload/data/bomb.gif
kennytestupload/data/boom.wav
kennytestupload/data/brick.png
kennytestupload/data/car_door.wav
kennytestupload/data/chimp.png
kennytestupload/data/city.png
kennytestupload/data/crimson.pnm
kennytestupload/data/cursor.png
kennytestupload/data/danger.gif
kennytestupload/data/enemy.png
kennytestupload/data/enemy2.png
kennytestupload/data/explosion1.gif
kennytestupload/data/fist.png
kennytestupload/data/green.pcx
kennytestupload/data/grey.pgm
kennytestupload/data/ground.png
kennytestupload/data/house_lo.mp3
kennytestupload/data/house_lo.ogg
kennytestupload/data/house_lo.wav
kennytestupload/data/laplacian.png
kennytestupload/data/liquid.bmp
kennytestupload/data/midikeys.png
kennytestupload/data/player1.gif
kennytestupload/data/punch.wav
kennytestupload/data/purple.xpm
kennytestupload/data/red.jpg
kennytestupload/data/sans.ttf
kennytestupload/data/scarlet.webp
kennytestupload/data/secosmic_lo.wav
kennytestupload/data/shot.gif
kennytestupload/data/static.png
kennytestupload/data/teal.svg
kennytestupload/data/turquoise.tif
kennytestupload/data/whiff.wav
kennytestupload/data/yellow.tga