Metadata-Version: 2.1
Name: kennytestupload
Version: 0.0.11
Summary: An demonstration of how to upload project to pypi.
Home-page: 
Author: Kenny C
Author-email: kennycheung388@yahoo.com.hk
License: MIT License
Keywords: tutorial
Classifier: Development Status :: 3 - Alpha
Classifier: License :: OSI Approved :: MIT License
